[
  {
    "PK": "EVENT#st6GLdflwQAvXqVbEBhlX#USER#VRMwIBTRTmLptAXmGY93Y",
    "SK": "ACTIVITY#2JroUYzeHVTGTtGgKH2nYxlh4TG",
    "type": "Activity",
    "id": "2JroUYzeHVTGTtGgKH2nYxlh4TG",
    "activityId": "5",
    "activityAt": "2023-01-04T15:19:38.559Z",
    "sessionId": "PszWru_pa-rp1STsfrAoo",
    "userId": "VRMwIBTRTmLptAXmGY93Y",
    "eventId": "st6GLdflwQAvXqVbEBhlX",
    "activityType": "sentiment",
    "channelId": "8",
    "videoTimeStamp": "2023-01-04T15:15:25.100Z",
    "deviceId": "DYwuKjuKKi6mMF-ri5juf",
    "GSI1PK": "EVENT#st6GLdflwQAvXqVbEBhlX#SESSION#Cd17oyzLRcrucTnbMAub",
    "GSI1SK": "ACTIVITY#SENTIMENT#2JroUYzeHVTGTtGgKH2nYxlh4TG"
  },
  {
    "PK": "EVENT#st6GLdflwQAvXqVbEBhlX#USER#VRMwIBTRTmLptAXmGY93Y",
    "SK": "ACTIVITY#2JroIvPjL3oHTsfmuIpkzapsqWM",
    "type": "Activity",
    "id": "2JroIvPjL3oHTsfmuIpkzapsqWM",
    "activityId": "7",
    "activityAt": "2023-01-04T15:18:06.501Z",
    "sessionId": "PszWru_pa-rp1STsfrAoo",
    "userId": "VRMwIBTRTmLptAXmGY93Y",
    "eventId": "st6GLdflwQAvXqVbEBhlX",
    "activityType": "sentiment",
    "channelId": "8",
    "videoTimeStamp": "2023-01-04T15:15:25.100Z",
    "deviceId": "DYwuKjuKKi6mMF-ri5juf",
    "GSI1PK": "EVENT#st6GLdflwQAvXqVbEBhlX#SESSION#Cd17oyzLRcrucTnbMAub",
    "GSI1SK": "ACTIVITY#SENTIMENT#2JroIvPjL3oHTsfmuIpkzapsqWM"
  },
  {
    "PK": "EVENT#st6GLdflwQAvXqVbEBhlX#USER#VRMwIBTRTmLptAXmGY93Y",
    "SK": "ACTIVITY#2Jro1NWZwJ0C5XijP3qyYUiISOP",
    "type": "Activity",
    "id": "2Jro1NWZwJ0C5XijP3qyYUiISOP",
    "activityId": "1",
    "activityAt": "2023-01-04T15:15:46.815Z",
    "sessionId": "PszWru_pa-rp1STsfrAoo",
    "userId": "VRMwIBTRTmLptAXmGY93Y",
    "eventId": "st6GLdflwQAvXqVbEBhlX",
    "activityType": "sentiment",
    "channelId": "8",
    "videoTimeStamp": "2023-01-04T15:15:25.100Z",
    "deviceId": "DYwuKjuKKi6mMF-ri5juf",
    "GSI1PK": "EVENT#st6GLdflwQAvXqVbEBhlX#SESSION#Cd17oyzLRcrucTnbMAub",
    "GSI1SK": "ACTIVITY#SENTIMENT#2Jro1NWZwJ0C5XijP3qyYUiISOP"
  },
  {
    "PK": "EVENT#st6GLdflwQAvXqVbEBhlX#USER#VRMwIBTRTmLptAXmGY93Y",
    "SK": "ACTIVITY#2JrbupPyQcaPQODQBsKtYJh3c6i",
    "type": "Activity",
    "id": "2JrbupPyQcaPQODQBsKtYJh3c6i",
    "activityId": "5",
    "activityAt": "2023-01-04T13:36:14.682Z",
    "sessionId": "yLuec4TP9EpATEmEIkqgU",
    "userId": "VRMwIBTRTmLptAXmGY93Y",
    "eventId": "st6GLdflwQAvXqVbEBhlX",
    "activityType": "sentiment",
    "channelId": "8",
    "videoTimeStamp": "2023-01-04T13:32:50.676Z",
    "deviceId": "evqw5ZkzXJRCsG9wGcHNK",
    "GSI1PK": "EVENT#st6GLdflwQAvXqVbEBhlX#SESSION#PXjKAr2NFoHoIW7AssDFF",
    "GSI1SK": "ACTIVITY#SENTIMENT#2JrbupPyQcaPQODQBsKtYJh3c6i"
  },
  {
    "PK": "EVENT#st6GLdflwQAvXqVbEBhlX#USER#VRMwIBTRTmLptAXmGY93Y",
    "SK": "ACTIVITY#2JrbueExpg40sl9X6Q1jG5222nf",
    "type": "Activity",
    "id": "2JrbueExpg40sl9X6Q1jG5222nf",
    "activityId": "3",
    "activityAt": "2023-01-04T13:36:12.566Z",
    "sessionId": "yLuec4TP9EpATEmEIkqgU",
    "userId": "VRMwIBTRTmLptAXmGY93Y",
    "eventId": "st6GLdflwQAvXqVbEBhlX",
    "activityType": "sentiment",
    "channelId": "8",
    "videoTimeStamp": "2023-01-04T13:32:50.676Z",
    "deviceId": "evqw5ZkzXJRCsG9wGcHNK",
    "GSI1PK": "EVENT#st6GLdflwQAvXqVbEBhlX#SESSION#PXjKAr2NFoHoIW7AssDFF",
    "GSI1SK": "ACTIVITY#SENTIMENT#2JrbueExpg40sl9X6Q1jG5222nf"
  },
  {
    "PK": "EVENT#st6GLdflwQAvXqVbEBhlX#USER#VRMwIBTRTmLptAXmGY93Y",
    "SK": "ACTIVITY#2Jrbfm0dChsD9vFo648jf3JnVdn",
    "type": "Activity",
    "id": "2Jrbfm0dChsD9vFo648jf3JnVdn",
    "activityId": "7",
    "activityAt": "2023-01-04T13:34:14.686Z",
    "sessionId": "yLuec4TP9EpATEmEIkqgU",
    "userId": "VRMwIBTRTmLptAXmGY93Y",
    "eventId": "st6GLdflwQAvXqVbEBhlX",
    "activityType": "sentiment",
    "channelId": "8",
    "videoTimeStamp": "2023-01-04T13:32:04.676Z",
    "deviceId": "evqw5ZkzXJRCsG9wGcHNK",
    "GSI1PK": "EVENT#st6GLdflwQAvXqVbEBhlX#SESSION#PXjKAr2NFoHoIW7AssDFF",
    "GSI1SK": "ACTIVITY#SENTIMENT#2Jrbfm0dChsD9vFo648jf3JnVdn"
  },
  {
    "PK": "EVENT#st6GLdflwQAvXqVbEBhlX#USER#VRMwIBTRTmLptAXmGY93Y",
    "SK": "ACTIVITY#2JrbfnwQU6WhajZLwbaIV9U8VQq",
    "type": "Activity",
    "id": "2JrbfnwQU6WhajZLwbaIV9U8VQq",
    "activityId": "6",
    "activityAt": "2023-01-04T13:34:14.280Z",
    "sessionId": "yLuec4TP9EpATEmEIkqgU",
    "userId": "VRMwIBTRTmLptAXmGY93Y",
    "eventId": "st6GLdflwQAvXqVbEBhlX",
    "activityType": "sentiment",
    "channelId": "8",
    "videoTimeStamp": "2023-01-04T13:32:04.676Z",
    "deviceId": "evqw5ZkzXJRCsG9wGcHNK",
    "GSI1PK": "EVENT#st6GLdflwQAvXqVbEBhlX#SESSION#PXjKAr2NFoHoIW7AssDFF",
    "GSI1SK": "ACTIVITY#SENTIMENT#2JrbfnwQU6WhajZLwbaIV9U8VQq"
  },
  {
    "PK": "EVENT#st6GLdflwQAvXqVbEBhlX#USER#VRMwIBTRTmLptAXmGY93Y",
    "SK": "ACTIVITY#2Jrbfek1djDOGWCJDuMQXbpqfmC",
    "type": "Activity",
    "id": "2Jrbfek1djDOGWCJDuMQXbpqfmC",
    "activityId": "5",
    "activityAt": "2023-01-04T13:34:13.872Z",
    "sessionId": "yLuec4TP9EpATEmEIkqgU",
    "userId": "VRMwIBTRTmLptAXmGY93Y",
    "eventId": "st6GLdflwQAvXqVbEBhlX",
    "activityType": "sentiment",
    "channelId": "8",
    "videoTimeStamp": "2023-01-04T13:32:04.676Z",
    "deviceId": "evqw5ZkzXJRCsG9wGcHNK",
    "GSI1PK": "EVENT#st6GLdflwQAvXqVbEBhlX#SESSION#PXjKAr2NFoHoIW7AssDFF",
    "GSI1SK": "ACTIVITY#SENTIMENT#2Jrbfek1djDOGWCJDuMQXbpqfmC"
  },
  {
    "PK": "EVENT#st6GLdflwQAvXqVbEBhlX#USER#VRMwIBTRTmLptAXmGY93Y",
    "SK": "ACTIVITY#2JrbfhEPPKi1dhGepK6z8UUv7dW",
    "type": "Activity",
    "id": "2JrbfhEPPKi1dhGepK6z8UUv7dW",
    "activityId": "4",
    "activityAt": "2023-01-04T13:34:13.672Z",
    "sessionId": "yLuec4TP9EpATEmEIkqgU",
    "userId": "VRMwIBTRTmLptAXmGY93Y",
    "eventId": "st6GLdflwQAvXqVbEBhlX",
    "activityType": "sentiment",
    "channelId": "8",
    "videoTimeStamp": "2023-01-04T13:32:04.676Z",
    "deviceId": "evqw5ZkzXJRCsG9wGcHNK",
    "GSI1PK": "EVENT#st6GLdflwQAvXqVbEBhlX#SESSION#PXjKAr2NFoHoIW7AssDFF",
    "GSI1SK": "ACTIVITY#SENTIMENT#2JrbfhEPPKi1dhGepK6z8UUv7dW"
  },
  {
    "PK": "EVENT#st6GLdflwQAvXqVbEBhlX#USER#VRMwIBTRTmLptAXmGY93Y",
    "SK": "ACTIVITY#2Jrbfh8Evz8hJpbJBWJW7ZCEWUA",
    "type": "Activity",
    "id": "2Jrbfh8Evz8hJpbJBWJW7ZCEWUA",
    "activityId": "3",
    "activityAt": "2023-01-04T13:34:13.029Z",
    "sessionId": "yLuec4TP9EpATEmEIkqgU",
    "userId": "VRMwIBTRTmLptAXmGY93Y",
    "eventId": "st6GLdflwQAvXqVbEBhlX",
    "activityType": "sentiment",
    "channelId": "8",
    "videoTimeStamp": "2023-01-04T13:32:04.676Z",
    "deviceId": "evqw5ZkzXJRCsG9wGcHNK",
    "GSI1PK": "EVENT#st6GLdflwQAvXqVbEBhlX#SESSION#PXjKAr2NFoHoIW7AssDFF",
    "GSI1SK": "ACTIVITY#SENTIMENT#2Jrbfh8Evz8hJpbJBWJW7ZCEWUA"
  },
  {
    "PK": "EVENT#st6GLdflwQAvXqVbEBhlX#USER#VRMwIBTRTmLptAXmGY93Y",
    "SK": "ACTIVITY#2JrbfVx4B9gtbXbNucmvNxA3rJg",
    "type": "Activity",
    "id": "2JrbfVx4B9gtbXbNucmvNxA3rJg",
    "activityId": "2",
    "activityAt": "2023-01-04T13:34:12.577Z",
    "sessionId": "yLuec4TP9EpATEmEIkqgU",
    "userId": "VRMwIBTRTmLptAXmGY93Y",
    "eventId": "st6GLdflwQAvXqVbEBhlX",
    "activityType": "sentiment",
    "channelId": "8",
    "videoTimeStamp": "2023-01-04T13:32:04.676Z",
    "deviceId": "evqw5ZkzXJRCsG9wGcHNK",
    "GSI1PK": "EVENT#st6GLdflwQAvXqVbEBhlX#SESSION#PXjKAr2NFoHoIW7AssDFF",
    "GSI1SK": "ACTIVITY#SENTIMENT#2JrbfVx4B9gtbXbNucmvNxA3rJg"
  },
  {
    "PK": "EVENT#st6GLdflwQAvXqVbEBhlX#USER#VRMwIBTRTmLptAXmGY93Y",
    "SK": "ACTIVITY#2Jrbfa9fdvm9dH5TB6Pio7uZ7rI",
    "type": "Activity",
    "id": "2Jrbfa9fdvm9dH5TB6Pio7uZ7rI",
    "activityId": "1",
    "activityAt": "2023-01-04T13:34:12.053Z",
    "sessionId": "yLuec4TP9EpATEmEIkqgU",
    "userId": "VRMwIBTRTmLptAXmGY93Y",
    "eventId": "st6GLdflwQAvXqVbEBhlX",
    "activityType": "sentiment",
    "channelId": "8",
    "videoTimeStamp": "2023-01-04T13:32:04.676Z",
    "deviceId": "evqw5ZkzXJRCsG9wGcHNK",
    "GSI1PK": "EVENT#st6GLdflwQAvXqVbEBhlX#SESSION#PXjKAr2NFoHoIW7AssDFF",
    "GSI1SK": "ACTIVITY#SENTIMENT#2Jrbfa9fdvm9dH5TB6Pio7uZ7rI"
  },
  {
    "PK": "EVENT#st6GLdflwQAvXqVbEBhlX#USER#VRMwIBTRTmLptAXmGY93Y",
    "SK": "ACTIVITY#2Jrbd1YhxWlL7ZOax38U3N7D9BM",
    "type": "Activity",
    "id": "2Jrbd1YhxWlL7ZOax38U3N7D9BM",
    "activityId": "4",
    "activityAt": "2023-01-04T13:33:52.641Z",
    "sessionId": "LqiuBB8lih6NTs80q_n5P",
    "userId": "VRMwIBTRTmLptAXmGY93Y",
    "eventId": "st6GLdflwQAvXqVbEBhlX",
    "activityType": "sentiment",
    "channelId": "8",
    "videoTimeStamp": "2023-01-04T13:33:11.716Z",
    "deviceId": "ccM112zVF5j4UVlh4ga7F",
    "GSI1PK": "EVENT#st6GLdflwQAvXqVbEBhlX#SESSION#PXjKAr2NFoHoIW7AssDFF",
    "GSI1SK": "ACTIVITY#SENTIMENT#2Jrbd1YhxWlL7ZOax38U3N7D9BM"
  },
  {
    "PK": "EVENT#st6GLdflwQAvXqVbEBhlX#USER#VRMwIBTRTmLptAXmGY93Y",
    "SK": "ACTIVITY#2JrbcdQHW1DyfQCRHn3RP89RDYm",
    "type": "Activity",
    "id": "2JrbcdQHW1DyfQCRHn3RP89RDYm",
    "activityId": "4",
    "activityAt": "2023-01-04T13:33:49.539Z",
    "sessionId": "LqiuBB8lih6NTs80q_n5P",
    "userId": "VRMwIBTRTmLptAXmGY93Y",
    "eventId": "st6GLdflwQAvXqVbEBhlX",
    "activityType": "sentiment",
    "channelId": "8",
    "videoTimeStamp": "2023-01-04T13:33:11.716Z",
    "deviceId": "ccM112zVF5j4UVlh4ga7F",
    "GSI1PK": "EVENT#st6GLdflwQAvXqVbEBhlX#SESSION#PXjKAr2NFoHoIW7AssDFF",
    "GSI1SK": "ACTIVITY#SENTIMENT#2JrbcdQHW1DyfQCRHn3RP89RDYm"
  },
  {
    "PK": "EVENT#st6GLdflwQAvXqVbEBhlX#USER#VRMwIBTRTmLptAXmGY93Y",
    "SK": "ACTIVITY#2JrbcUrj8klbULR8KnvKVgfG9hv",
    "type": "Activity",
    "id": "2JrbcUrj8klbULR8KnvKVgfG9hv",
    "activityId": "3",
    "activityAt": "2023-01-04T13:33:48.907Z",
    "sessionId": "LqiuBB8lih6NTs80q_n5P",
    "userId": "VRMwIBTRTmLptAXmGY93Y",
    "eventId": "st6GLdflwQAvXqVbEBhlX",
    "activityType": "sentiment",
    "channelId": "8",
    "videoTimeStamp": "2023-01-04T13:33:11.716Z",
    "deviceId": "ccM112zVF5j4UVlh4ga7F",
    "GSI1PK": "EVENT#st6GLdflwQAvXqVbEBhlX#SESSION#PXjKAr2NFoHoIW7AssDFF",
    "GSI1SK": "ACTIVITY#SENTIMENT#2JrbcUrj8klbULR8KnvKVgfG9hv"
  },
  {
    "PK": "EVENT#st6GLdflwQAvXqVbEBhlX#USER#VRMwIBTRTmLptAXmGY93Y",
    "SK": "ACTIVITY#2Jrba7e5LKyHUYv2tqiGMyhaGEu",
    "type": "Activity",
    "id": "2Jrba7e5LKyHUYv2tqiGMyhaGEu",
    "activityId": "2",
    "activityAt": "2023-01-04T13:33:29.769Z",
    "sessionId": "LqiuBB8lih6NTs80q_n5P",
    "userId": "VRMwIBTRTmLptAXmGY93Y",
    "eventId": "st6GLdflwQAvXqVbEBhlX",
    "activityType": "sentiment",
    "channelId": "8",
    "videoTimeStamp": "2023-01-04T13:33:11.716Z",
    "deviceId": "ccM112zVF5j4UVlh4ga7F",
    "GSI1PK": "EVENT#st6GLdflwQAvXqVbEBhlX#SESSION#PXjKAr2NFoHoIW7AssDFF",
    "GSI1SK": "ACTIVITY#SENTIMENT#2Jrba7e5LKyHUYv2tqiGMyhaGEu"
  },
  {
    "PK": "EVENT#st6GLdflwQAvXqVbEBhlX#USER#VRMwIBTRTmLptAXmGY93Y",
    "SK": "ACTIVITY#2Jrba9JvLNjc8bGtqea7NUnQFJs",
    "type": "Activity",
    "id": "2Jrba9JvLNjc8bGtqea7NUnQFJs",
    "activityId": "6",
    "activityAt": "2023-01-04T13:33:29.656Z",
    "sessionId": "LqiuBB8lih6NTs80q_n5P",
    "userId": "VRMwIBTRTmLptAXmGY93Y",
    "eventId": "st6GLdflwQAvXqVbEBhlX",
    "activityType": "sentiment",
    "channelId": "8",
    "videoTimeStamp": "2023-01-04T13:33:11.716Z",
    "deviceId": "ccM112zVF5j4UVlh4ga7F",
    "GSI1PK": "EVENT#st6GLdflwQAvXqVbEBhlX#SESSION#PXjKAr2NFoHoIW7AssDFF",
    "GSI1SK": "ACTIVITY#SENTIMENT#2Jrba9JvLNjc8bGtqea7NUnQFJs"
  },
  {
    "PK": "EVENT#st6GLdflwQAvXqVbEBhlX#USER#VRMwIBTRTmLptAXmGY93Y",
    "SK": "ACTIVITY#2Jrba8ypMWS4SHzXKlwCWwSIVph",
    "type": "Activity",
    "id": "2Jrba8ypMWS4SHzXKlwCWwSIVph",
    "activityId": "6",
    "activityAt": "2023-01-04T13:33:29.022Z",
    "sessionId": "LqiuBB8lih6NTs80q_n5P",
    "userId": "VRMwIBTRTmLptAXmGY93Y",
    "eventId": "st6GLdflwQAvXqVbEBhlX",
    "activityType": "sentiment",
    "channelId": "8",
    "videoTimeStamp": "2023-01-04T13:33:11.716Z",
    "deviceId": "ccM112zVF5j4UVlh4ga7F",
    "GSI1PK": "EVENT#st6GLdflwQAvXqVbEBhlX#SESSION#PXjKAr2NFoHoIW7AssDFF",
    "GSI1SK": "ACTIVITY#SENTIMENT#2Jrba8ypMWS4SHzXKlwCWwSIVph"
  },
  {
    "PK": "EVENT#st6GLdflwQAvXqVbEBhlX#USER#VRMwIBTRTmLptAXmGY93Y",
    "SK": "ACTIVITY#2Jrba3Q7JYbM6VGvbrg5o1y1fOZ",
    "type": "Activity",
    "id": "2Jrba3Q7JYbM6VGvbrg5o1y1fOZ",
    "activityId": "6",
    "activityAt": "2023-01-04T13:33:28.903Z",
    "sessionId": "LqiuBB8lih6NTs80q_n5P",
    "userId": "VRMwIBTRTmLptAXmGY93Y",
    "eventId": "st6GLdflwQAvXqVbEBhlX",
    "activityType": "sentiment",
    "channelId": "8",
    "videoTimeStamp": "2023-01-04T13:33:11.716Z",
    "deviceId": "ccM112zVF5j4UVlh4ga7F",
    "GSI1PK": "EVENT#st6GLdflwQAvXqVbEBhlX#SESSION#PXjKAr2NFoHoIW7AssDFF",
    "GSI1SK": "ACTIVITY#SENTIMENT#2Jrba3Q7JYbM6VGvbrg5o1y1fOZ"
  },
  {
    "PK": "EVENT#st6GLdflwQAvXqVbEBhlX#USER#VRMwIBTRTmLptAXmGY93Y",
    "SK": "ACTIVITY#2Jrba2I7yPq1tXoBChfZV7c9BeG",
    "type": "Activity",
    "id": "2Jrba2I7yPq1tXoBChfZV7c9BeG",
    "activityId": "5",
    "activityAt": "2023-01-04T13:33:28.298Z",
    "sessionId": "LqiuBB8lih6NTs80q_n5P",
    "userId": "VRMwIBTRTmLptAXmGY93Y",
    "eventId": "st6GLdflwQAvXqVbEBhlX",
    "activityType": "sentiment",
    "channelId": "8",
    "videoTimeStamp": "2023-01-04T13:33:11.716Z",
    "deviceId": "ccM112zVF5j4UVlh4ga7F",
    "GSI1PK": "EVENT#st6GLdflwQAvXqVbEBhlX#SESSION#PXjKAr2NFoHoIW7AssDFF",
    "GSI1SK": "ACTIVITY#SENTIMENT#2Jrba2I7yPq1tXoBChfZV7c9BeG"
  },
  {
    "PK": "EVENT#st6GLdflwQAvXqVbEBhlX#USER#VRMwIBTRTmLptAXmGY93Y",
    "SK": "ACTIVITY#2JrbZswqLuo1i1gR0beQuKTaxwL",
    "type": "Activity",
    "id": "2JrbZswqLuo1i1gR0beQuKTaxwL",
    "activityId": "1",
    "activityAt": "2023-01-04T13:33:27.670Z",
    "sessionId": "LqiuBB8lih6NTs80q_n5P",
    "userId": "VRMwIBTRTmLptAXmGY93Y",
    "eventId": "st6GLdflwQAvXqVbEBhlX",
    "activityType": "sentiment",
    "channelId": "8",
    "videoTimeStamp": "2023-01-04T13:33:11.716Z",
    "deviceId": "ccM112zVF5j4UVlh4ga7F",
    "GSI1PK": "EVENT#st6GLdflwQAvXqVbEBhlX#SESSION#PXjKAr2NFoHoIW7AssDFF",
    "GSI1SK": "ACTIVITY#SENTIMENT#2JrbZswqLuo1i1gR0beQuKTaxwL"
  },
  {
    "PK": "EVENT#st6GLdflwQAvXqVbEBhlX#USER#VRMwIBTRTmLptAXmGY93Y",
    "SK": "ACTIVITY#2JrbZtQVA11hJ1WvCnM3KMnBNKV",
    "type": "Activity",
    "id": "2JrbZtQVA11hJ1WvCnM3KMnBNKV",
    "activityId": "1",
    "activityAt": "2023-01-04T13:33:27.524Z",
    "sessionId": "LqiuBB8lih6NTs80q_n5P",
    "userId": "VRMwIBTRTmLptAXmGY93Y",
    "eventId": "st6GLdflwQAvXqVbEBhlX",
    "activityType": "sentiment",
    "channelId": "8",
    "videoTimeStamp": "2023-01-04T13:33:11.716Z",
    "deviceId": "ccM112zVF5j4UVlh4ga7F",
    "GSI1PK": "EVENT#st6GLdflwQAvXqVbEBhlX#SESSION#PXjKAr2NFoHoIW7AssDFF",
    "GSI1SK": "ACTIVITY#SENTIMENT#2JrbZtQVA11hJ1WvCnM3KMnBNKV"
  },
  {
    "PK": "EVENT#st6GLdflwQAvXqVbEBhlX#USER#VRMwIBTRTmLptAXmGY93Y",
    "SK": "ACTIVITY#2JrbZta58qtjGLQLaJtDS3olYHH",
    "type": "Activity",
    "id": "2JrbZta58qtjGLQLaJtDS3olYHH",
    "activityId": "1",
    "activityAt": "2023-01-04T13:33:27.136Z",
    "sessionId": "LqiuBB8lih6NTs80q_n5P",
    "userId": "VRMwIBTRTmLptAXmGY93Y",
    "eventId": "st6GLdflwQAvXqVbEBhlX",
    "activityType": "sentiment",
    "channelId": "8",
    "videoTimeStamp": "2023-01-04T13:33:11.716Z",
    "deviceId": "ccM112zVF5j4UVlh4ga7F",
    "GSI1PK": "EVENT#st6GLdflwQAvXqVbEBhlX#SESSION#PXjKAr2NFoHoIW7AssDFF",
    "GSI1SK": "ACTIVITY#SENTIMENT#2JrbZta58qtjGLQLaJtDS3olYHH"
  },
  {
    "PK": "EVENT#st6GLdflwQAvXqVbEBhlX#USER#VRMwIBTRTmLptAXmGY93Y",
    "SK": "ACTIVITY#2JrbXdlBeOP0oHAXJWBoutY3Sp3",
    "type": "Activity",
    "id": "2JrbXdlBeOP0oHAXJWBoutY3Sp3",
    "activityId": "7",
    "activityAt": "2023-01-04T13:33:09.888Z",
    "sessionId": "yLuec4TP9EpATEmEIkqgU",
    "userId": "VRMwIBTRTmLptAXmGY93Y",
    "eventId": "st6GLdflwQAvXqVbEBhlX",
    "activityType": "sentiment",
    "channelId": "8",
    "videoTimeStamp": "2023-01-04T13:32:04.676Z",
    "deviceId": "evqw5ZkzXJRCsG9wGcHNK",
    "GSI1PK": "EVENT#st6GLdflwQAvXqVbEBhlX#SESSION#PXjKAr2NFoHoIW7AssDFF",
    "GSI1SK": "ACTIVITY#SENTIMENT#2JrbXdlBeOP0oHAXJWBoutY3Sp3"
  },
  {
    "PK": "EVENT#st6GLdflwQAvXqVbEBhlX#USER#VRMwIBTRTmLptAXmGY93Y",
    "SK": "ACTIVITY#2JrbXaWJzR9ajm2sQZ6RgayEZIK",
    "type": "Activity",
    "id": "2JrbXaWJzR9ajm2sQZ6RgayEZIK",
    "activityId": "6",
    "activityAt": "2023-01-04T13:33:09.799Z",
    "sessionId": "yLuec4TP9EpATEmEIkqgU",
    "userId": "VRMwIBTRTmLptAXmGY93Y",
    "eventId": "st6GLdflwQAvXqVbEBhlX",
    "activityType": "sentiment",
    "channelId": "8",
    "videoTimeStamp": "2023-01-04T13:32:04.676Z",
    "deviceId": "evqw5ZkzXJRCsG9wGcHNK",
    "GSI1PK": "EVENT#st6GLdflwQAvXqVbEBhlX#SESSION#PXjKAr2NFoHoIW7AssDFF",
    "GSI1SK": "ACTIVITY#SENTIMENT#2JrbXaWJzR9ajm2sQZ6RgayEZIK"
  },
  {
    "PK": "EVENT#st6GLdflwQAvXqVbEBhlX#USER#VRMwIBTRTmLptAXmGY93Y",
    "SK": "ACTIVITY#2JrbXf6d4XfHO06MXQbnkcBF47m",
    "type": "Activity",
    "id": "2JrbXf6d4XfHO06MXQbnkcBF47m",
    "activityId": "5",
    "activityAt": "2023-01-04T13:33:09.531Z",
    "sessionId": "yLuec4TP9EpATEmEIkqgU",
    "userId": "VRMwIBTRTmLptAXmGY93Y",
    "eventId": "st6GLdflwQAvXqVbEBhlX",
    "activityType": "sentiment",
    "channelId": "8",
    "videoTimeStamp": "2023-01-04T13:32:04.676Z",
    "deviceId": "evqw5ZkzXJRCsG9wGcHNK",
    "GSI1PK": "EVENT#st6GLdflwQAvXqVbEBhlX#SESSION#PXjKAr2NFoHoIW7AssDFF",
    "GSI1SK": "ACTIVITY#SENTIMENT#2JrbXf6d4XfHO06MXQbnkcBF47m"
  },
  {
    "PK": "EVENT#st6GLdflwQAvXqVbEBhlX#USER#VRMwIBTRTmLptAXmGY93Y",
    "SK": "ACTIVITY#2JrbXTl8WDFX5qY63LJWtrYM95h",
    "type": "Activity",
    "id": "2JrbXTl8WDFX5qY63LJWtrYM95h",
    "activityId": "4",
    "activityAt": "2023-01-04T13:33:08.766Z",
    "sessionId": "yLuec4TP9EpATEmEIkqgU",
    "userId": "VRMwIBTRTmLptAXmGY93Y",
    "eventId": "st6GLdflwQAvXqVbEBhlX",
    "activityType": "sentiment",
    "channelId": "8",
    "videoTimeStamp": "2023-01-04T13:32:04.676Z",
    "deviceId": "evqw5ZkzXJRCsG9wGcHNK",
    "GSI1PK": "EVENT#st6GLdflwQAvXqVbEBhlX#SESSION#PXjKAr2NFoHoIW7AssDFF",
    "GSI1SK": "ACTIVITY#SENTIMENT#2JrbXTl8WDFX5qY63LJWtrYM95h"
  },
  {
    "PK": "EVENT#st6GLdflwQAvXqVbEBhlX#USER#VRMwIBTRTmLptAXmGY93Y",
    "SK": "ACTIVITY#2JrbXYDzSsvL1QAUjbYzTtUO8i7",
    "type": "Activity",
    "id": "2JrbXYDzSsvL1QAUjbYzTtUO8i7",
    "activityId": "3",
    "activityAt": "2023-01-04T13:33:08.253Z",
    "sessionId": "yLuec4TP9EpATEmEIkqgU",
    "userId": "VRMwIBTRTmLptAXmGY93Y",
    "eventId": "st6GLdflwQAvXqVbEBhlX",
    "activityType": "sentiment",
    "channelId": "8",
    "videoTimeStamp": "2023-01-04T13:32:04.676Z",
    "deviceId": "evqw5ZkzXJRCsG9wGcHNK",
    "GSI1PK": "EVENT#st6GLdflwQAvXqVbEBhlX#SESSION#PXjKAr2NFoHoIW7AssDFF",
    "GSI1SK": "ACTIVITY#SENTIMENT#2JrbXYDzSsvL1QAUjbYzTtUO8i7"
  },
  {
    "PK": "EVENT#st6GLdflwQAvXqVbEBhlX#USER#VRMwIBTRTmLptAXmGY93Y",
    "SK": "ACTIVITY#2JrbXRHxPIfCzA4KEOT4X60XYCK",
    "type": "Activity",
    "id": "2JrbXRHxPIfCzA4KEOT4X60XYCK",
    "activityId": "2",
    "activityAt": "2023-01-04T13:33:07.733Z",
    "sessionId": "yLuec4TP9EpATEmEIkqgU",
    "userId": "VRMwIBTRTmLptAXmGY93Y",
    "eventId": "st6GLdflwQAvXqVbEBhlX",
    "activityType": "sentiment",
    "channelId": "8",
    "videoTimeStamp": "2023-01-04T13:32:04.676Z",
    "deviceId": "evqw5ZkzXJRCsG9wGcHNK",
    "GSI1PK": "EVENT#st6GLdflwQAvXqVbEBhlX#SESSION#PXjKAr2NFoHoIW7AssDFF",
    "GSI1SK": "ACTIVITY#SENTIMENT#2JrbXRHxPIfCzA4KEOT4X60XYCK"
  },
  {
    "PK": "EVENT#st6GLdflwQAvXqVbEBhlX#USER#VRMwIBTRTmLptAXmGY93Y",
    "SK": "ACTIVITY#2JrbXCXLdx2uYSKVWeRJRYQPWBE",
    "type": "Activity",
    "id": "2JrbXCXLdx2uYSKVWeRJRYQPWBE",
    "activityId": "1",
    "activityAt": "2023-01-04T13:33:06.873Z",
    "sessionId": "yLuec4TP9EpATEmEIkqgU",
    "userId": "VRMwIBTRTmLptAXmGY93Y",
    "eventId": "st6GLdflwQAvXqVbEBhlX",
    "activityType": "sentiment",
    "channelId": "8",
    "videoTimeStamp": "2023-01-04T13:32:04.676Z",
    "deviceId": "evqw5ZkzXJRCsG9wGcHNK",
    "GSI1PK": "EVENT#st6GLdflwQAvXqVbEBhlX#SESSION#PXjKAr2NFoHoIW7AssDFF",
    "GSI1SK": "ACTIVITY#SENTIMENT#2JrbXCXLdx2uYSKVWeRJRYQPWBE"
  },
  {
    "PK": "EVENT#st6GLdflwQAvXqVbEBhlX#USER#VRMwIBTRTmLptAXmGY93Y",
    "SK": "ACTIVITY#2JrbWfetLONEowDr5tNNgInPjTS",
    "type": "Activity",
    "id": "2JrbWfetLONEowDr5tNNgInPjTS",
    "activityId": "7",
    "activityAt": "2023-01-04T13:33:01.784Z",
    "sessionId": "Pk6hg6IyZmApH5w_oQiHg",
    "userId": "VRMwIBTRTmLptAXmGY93Y",
    "eventId": "st6GLdflwQAvXqVbEBhlX",
    "activityType": "sentiment",
    "channelId": "8",
    "videoTimeStamp": "2023-01-04T13:33:54.398Z",
    "deviceId": "-ZTo2TeQGIizxtm_3Vrew",
    "GSI1PK": "EVENT#st6GLdflwQAvXqVbEBhlX#SESSION#PXjKAr2NFoHoIW7AssDFF",
    "GSI1SK": "ACTIVITY#SENTIMENT#2JrbWfetLONEowDr5tNNgInPjTS"
  },
  {
    "PK": "EVENT#st6GLdflwQAvXqVbEBhlX#USER#VRMwIBTRTmLptAXmGY93Y",
    "SK": "ACTIVITY#2JrbW1J4CMChxNCQxREIO3YZDzt",
    "type": "Activity",
    "id": "2JrbW1J4CMChxNCQxREIO3YZDzt",
    "activityId": "6",
    "activityAt": "2023-01-04T13:32:56.642Z",
    "sessionId": "Pk6hg6IyZmApH5w_oQiHg",
    "userId": "VRMwIBTRTmLptAXmGY93Y",
    "eventId": "st6GLdflwQAvXqVbEBhlX",
    "activityType": "sentiment",
    "channelId": "8",
    "videoTimeStamp": "2023-01-04T13:33:48.398Z",
    "deviceId": "-ZTo2TeQGIizxtm_3Vrew",
    "GSI1PK": "EVENT#st6GLdflwQAvXqVbEBhlX#SESSION#PXjKAr2NFoHoIW7AssDFF",
    "GSI1SK": "ACTIVITY#SENTIMENT#2JrbW1J4CMChxNCQxREIO3YZDzt"
  },
  {
    "PK": "EVENT#st6GLdflwQAvXqVbEBhlX#USER#VRMwIBTRTmLptAXmGY93Y",
    "SK": "ACTIVITY#2JrbVLTeeBculE2BkjEXP7t0RZB",
    "type": "Activity",
    "id": "2JrbVLTeeBculE2BkjEXP7t0RZB",
    "activityId": "3",
    "activityAt": "2023-01-04T13:32:51.551Z",
    "sessionId": "Pk6hg6IyZmApH5w_oQiHg",
    "userId": "VRMwIBTRTmLptAXmGY93Y",
    "eventId": "st6GLdflwQAvXqVbEBhlX",
    "activityType": "sentiment",
    "channelId": "8",
    "videoTimeStamp": "2023-01-04T13:33:43.398Z",
    "deviceId": "-ZTo2TeQGIizxtm_3Vrew",
    "GSI1PK": "EVENT#st6GLdflwQAvXqVbEBhlX#SESSION#PXjKAr2NFoHoIW7AssDFF",
    "GSI1SK": "ACTIVITY#SENTIMENT#2JrbVLTeeBculE2BkjEXP7t0RZB"
  },
  {
    "PK": "EVENT#st6GLdflwQAvXqVbEBhlX#USER#VRMwIBTRTmLptAXmGY93Y",
    "SK": "ACTIVITY#2JrbUk7iboS7WbBIyBdu4bJ60pR",
    "type": "Activity",
    "id": "2JrbUk7iboS7WbBIyBdu4bJ60pR",
    "activityId": "4",
    "activityAt": "2023-01-04T13:32:46.510Z",
    "sessionId": "Pk6hg6IyZmApH5w_oQiHg",
    "userId": "VRMwIBTRTmLptAXmGY93Y",
    "eventId": "st6GLdflwQAvXqVbEBhlX",
    "activityType": "sentiment",
    "channelId": "8",
    "videoTimeStamp": "2023-01-04T13:33:38.398Z",
    "deviceId": "-ZTo2TeQGIizxtm_3Vrew",
    "GSI1PK": "EVENT#st6GLdflwQAvXqVbEBhlX#SESSION#PXjKAr2NFoHoIW7AssDFF",
    "GSI1SK": "ACTIVITY#SENTIMENT#2JrbUk7iboS7WbBIyBdu4bJ60pR"
  },
  {
    "PK": "EVENT#st6GLdflwQAvXqVbEBhlX#USER#VRMwIBTRTmLptAXmGY93Y",
    "SK": "ACTIVITY#2JrbTItdibOCobEcVD9IYkLqL7J",
    "type": "Activity",
    "id": "2JrbTItdibOCobEcVD9IYkLqL7J",
    "activityId": "4",
    "activityAt": "2023-01-04T13:32:35.917Z",
    "sessionId": "yLuec4TP9EpATEmEIkqgU",
    "userId": "VRMwIBTRTmLptAXmGY93Y",
    "eventId": "st6GLdflwQAvXqVbEBhlX",
    "activityType": "sentiment",
    "channelId": "8",
    "videoTimeStamp": "2023-01-04T13:32:04.676Z",
    "deviceId": "evqw5ZkzXJRCsG9wGcHNK",
    "GSI1PK": "EVENT#st6GLdflwQAvXqVbEBhlX#SESSION#PXjKAr2NFoHoIW7AssDFF",
    "GSI1SK": "ACTIVITY#SENTIMENT#2JrbTItdibOCobEcVD9IYkLqL7J"
  },
  {
    "PK": "EVENT#st6GLdflwQAvXqVbEBhlX#USER#VRMwIBTRTmLptAXmGY93Y",
    "SK": "ACTIVITY#2JrbT5gA7qjgddcr0cnw39QRgVb",
    "type": "Activity",
    "id": "2JrbT5gA7qjgddcr0cnw39QRgVb",
    "activityId": "5",
    "activityAt": "2023-01-04T13:32:33.749Z",
    "sessionId": "yLuec4TP9EpATEmEIkqgU",
    "userId": "VRMwIBTRTmLptAXmGY93Y",
    "eventId": "st6GLdflwQAvXqVbEBhlX",
    "activityType": "sentiment",
    "channelId": "8",
    "videoTimeStamp": "2023-01-04T13:32:04.676Z",
    "deviceId": "evqw5ZkzXJRCsG9wGcHNK",
    "GSI1PK": "EVENT#st6GLdflwQAvXqVbEBhlX#SESSION#PXjKAr2NFoHoIW7AssDFF",
    "GSI1SK": "ACTIVITY#SENTIMENT#2JrbT5gA7qjgddcr0cnw39QRgVb"
  },
  {
    "PK": "EVENT#st6GLdflwQAvXqVbEBhlX#USER#VRMwIBTRTmLptAXmGY93Y",
    "SK": "ACTIVITY#2JrbRD6WNxvdeYUg3fpnjdsYgR2",
    "type": "Activity",
    "id": "2JrbRD6WNxvdeYUg3fpnjdsYgR2",
    "activityId": "5",
    "activityAt": "2023-01-04T13:32:18.956Z",
    "sessionId": "yLuec4TP9EpATEmEIkqgU",
    "userId": "VRMwIBTRTmLptAXmGY93Y",
    "eventId": "st6GLdflwQAvXqVbEBhlX",
    "activityType": "sentiment",
    "channelId": "8",
    "videoTimeStamp": "2023-01-04T13:32:04.676Z",
    "deviceId": "evqw5ZkzXJRCsG9wGcHNK",
    "GSI1PK": "EVENT#st6GLdflwQAvXqVbEBhlX#SESSION#PXjKAr2NFoHoIW7AssDFF",
    "GSI1SK": "ACTIVITY#SENTIMENT#2JrbRD6WNxvdeYUg3fpnjdsYgR2"
  },
  {
    "PK": "EVENT#st6GLdflwQAvXqVbEBhlX#USER#VRMwIBTRTmLptAXmGY93Y",
    "SK": "ACTIVITY#2JrbQSPBNSR2275pD7Ma1tKzjs0",
    "type": "Activity",
    "id": "2JrbQSPBNSR2275pD7Ma1tKzjs0",
    "activityId": "1",
    "activityAt": "2023-01-04T13:32:12.940Z",
    "sessionId": "yLuec4TP9EpATEmEIkqgU",
    "userId": "VRMwIBTRTmLptAXmGY93Y",
    "eventId": "st6GLdflwQAvXqVbEBhlX",
    "activityType": "sentiment",
    "channelId": "8",
    "videoTimeStamp": "2023-01-04T13:32:04.676Z",
    "deviceId": "evqw5ZkzXJRCsG9wGcHNK",
    "GSI1PK": "EVENT#st6GLdflwQAvXqVbEBhlX#SESSION#PXjKAr2NFoHoIW7AssDFF",
    "GSI1SK": "ACTIVITY#SENTIMENT#2JrbQSPBNSR2275pD7Ma1tKzjs0"
  },
  {
    "PK": "EVENT#st6GLdflwQAvXqVbEBhlX#USER#VRMwIBTRTmLptAXmGY93Y",
    "SK": "ACTIVITY#2JrbQTf2Gx4lAaaIE80I26ySC3c",
    "type": "Activity",
    "id": "2JrbQTf2Gx4lAaaIE80I26ySC3c",
    "activityId": "2",
    "activityAt": "2023-01-04T13:32:12.122Z",
    "sessionId": "yLuec4TP9EpATEmEIkqgU",
    "userId": "VRMwIBTRTmLptAXmGY93Y",
    "eventId": "st6GLdflwQAvXqVbEBhlX",
    "activityType": "sentiment",
    "channelId": "8",
    "videoTimeStamp": "2023-01-04T13:32:04.676Z",
    "deviceId": "evqw5ZkzXJRCsG9wGcHNK",
    "GSI1PK": "EVENT#st6GLdflwQAvXqVbEBhlX#SESSION#PXjKAr2NFoHoIW7AssDFF",
    "GSI1SK": "ACTIVITY#SENTIMENT#2JrbQTf2Gx4lAaaIE80I26ySC3c"
  },
  {
    "PK": "EVENT#st6GLdflwQAvXqVbEBhlX#USER#VRMwIBTRTmLptAXmGY93Y",
    "SK": "ACTIVITY#2JrbQ8SJ8v4sUGGJVEZwfNCqjv9",
    "type": "Activity",
    "id": "2JrbQ8SJ8v4sUGGJVEZwfNCqjv9",
    "activityId": "3",
    "activityAt": "2023-01-04T13:32:09.844Z",
    "sessionId": "yLuec4TP9EpATEmEIkqgU",
    "userId": "VRMwIBTRTmLptAXmGY93Y",
    "eventId": "st6GLdflwQAvXqVbEBhlX",
    "activityType": "sentiment",
    "channelId": "8",
    "videoTimeStamp": "2023-01-04T13:32:04.676Z",
    "deviceId": "evqw5ZkzXJRCsG9wGcHNK",
    "GSI1PK": "EVENT#st6GLdflwQAvXqVbEBhlX#SESSION#PXjKAr2NFoHoIW7AssDFF",
    "GSI1SK": "ACTIVITY#SENTIMENT#2JrbQ8SJ8v4sUGGJVEZwfNCqjv9"
  },
  {
    "PK": "EVENT#st6GLdflwQAvXqVbEBhlX#USER#VRMwIBTRTmLptAXmGY93Y",
    "SK": "ACTIVITY#2JrbPT7OgsVEbs1OJGgD82e5RBd",
    "type": "Activity",
    "id": "2JrbPT7OgsVEbs1OJGgD82e5RBd",
    "activityId": "5",
    "activityAt": "2023-01-04T13:32:04.366Z",
    "sessionId": "yLuec4TP9EpATEmEIkqgU",
    "userId": "VRMwIBTRTmLptAXmGY93Y",
    "eventId": "st6GLdflwQAvXqVbEBhlX",
    "activityType": "sentiment",
    "channelId": "8",
    "videoTimeStamp": "2023-01-04T13:32:04.676Z",
    "deviceId": "evqw5ZkzXJRCsG9wGcHNK",
    "GSI1PK": "EVENT#st6GLdflwQAvXqVbEBhlX#SESSION#PXjKAr2NFoHoIW7AssDFF",
    "GSI1SK": "ACTIVITY#SENTIMENT#2JrbPT7OgsVEbs1OJGgD82e5RBd"
  },
  {
    "PK": "EVENT#st6GLdflwQAvXqVbEBhlX#USER#VRMwIBTRTmLptAXmGY93Y",
    "SK": "ACTIVITY#2JrbPITg532aa5p4odpO9bFf3QS",
    "type": "Activity",
    "id": "2JrbPITg532aa5p4odpO9bFf3QS",
    "activityId": "6",
    "activityAt": "2023-01-04T13:32:03.107Z",
    "sessionId": "yLuec4TP9EpATEmEIkqgU",
    "userId": "VRMwIBTRTmLptAXmGY93Y",
    "eventId": "st6GLdflwQAvXqVbEBhlX",
    "activityType": "sentiment",
    "channelId": "8",
    "videoTimeStamp": "2023-01-04T13:32:04.676Z",
    "deviceId": "evqw5ZkzXJRCsG9wGcHNK",
    "GSI1PK": "EVENT#st6GLdflwQAvXqVbEBhlX#SESSION#PXjKAr2NFoHoIW7AssDFF",
    "GSI1SK": "ACTIVITY#SENTIMENT#2JrbPITg532aa5p4odpO9bFf3QS"
  },
  {
    "PK": "EVENT#st6GLdflwQAvXqVbEBhlX#USER#VRMwIBTRTmLptAXmGY93Y",
    "SK": "ACTIVITY#2JrawEC78P96yYYKYCQEioe5zj7",
    "type": "Activity",
    "id": "2JrawEC78P96yYYKYCQEioe5zj7",
    "activityId": "1",
    "activityAt": "2023-01-04T13:28:11.623Z",
    "sessionId": "LqiuBB8lih6NTs80q_n5P",
    "userId": "VRMwIBTRTmLptAXmGY93Y",
    "eventId": "st6GLdflwQAvXqVbEBhlX",
    "activityType": "sentiment",
    "channelId": "8",
    "videoTimeStamp": "2023-01-04T13:28:13.940Z",
    "deviceId": "ccM112zVF5j4UVlh4ga7F",
    "GSI1PK": "EVENT#st6GLdflwQAvXqVbEBhlX#SESSION#PXjKAr2NFoHoIW7AssDFF",
    "GSI1SK": "ACTIVITY#SENTIMENT#2JrawEC78P96yYYKYCQEioe5zj7"
  },
  {
    "PK": "EVENT#st6GLdflwQAvXqVbEBhlX#USER#gEJXuQIpsShFo5ugrfdlK",
    "SK": "ACTIVITY#2JrUXIG7eqkKYJWH66YKdUue0vE",
    "type": "Activity",
    "id": "2JrUXIG7eqkKYJWH66YKdUue0vE",
    "activityId": "2",
    "activityAt": "2023-01-04T12:35:33.101Z",
    "sessionId": "43225aabduiadsnaTMY",
    "userId": "gEJXuQIpsShFo5ugrfdlK",
    "eventId": "st6GLdflwQAvXqVbEBhlX",
    "activityType": "sentiment",
    "channelId": "4",
    "videoTimeStamp": "2023-01-03T10:21:20.989Z",
    "deviceId": "137",
    "GSI1PK": "EVENT#st6GLdflwQAvXqVbEBhlX#SESSION#PXjKAr2NFoHoIW7AssDFF",
    "GSI1SK": "ACTIVITY#SENTIMENT#2JrUXIG7eqkKYJWH66YKdUue0vE"
  },
  {
    "PK": "EVENT#st6GLdflwQAvXqVbEBhlX#USER#gEJXuQIpsShFo5ugrfdlK",
    "SK": "ACTIVITY#2JrUWlBVWIom1CemaAyVZIOw73L",
    "type": "Activity",
    "id": "2JrUWlBVWIom1CemaAyVZIOw73L",
    "activityId": "3",
    "activityAt": "2023-01-04T12:35:29.211Z",
    "sessionId": "43225aabduiadsnaTMY",
    "userId": "gEJXuQIpsShFo5ugrfdlK",
    "eventId": "st6GLdflwQAvXqVbEBhlX",
    "activityType": "sentiment",
    "channelId": "4",
    "videoTimeStamp": "2023-01-03T10:21:20.989Z",
    "deviceId": "137",
    "GSI1PK": "EVENT#st6GLdflwQAvXqVbEBhlX#SESSION#PXjKAr2NFoHoIW7AssDFF",
    "GSI1SK": "ACTIVITY#SENTIMENT#2JrUWlBVWIom1CemaAyVZIOw73L"
  },
  {
    "PK": "EVENT#st6GLdflwQAvXqVbEBhlX#USER#gEJXuQIpsShFo5ugrfdlK",
    "SK": "ACTIVITY#2JrUWIRf5Adb5Ij7e2KEUyUuKEA",
    "type": "Activity",
    "id": "2JrUWIRf5Adb5Ij7e2KEUyUuKEA",
    "activityId": "4",
    "activityAt": "2023-01-04T12:35:25.759Z",
    "sessionId": "43225aabduiadsnaTMY",
    "userId": "gEJXuQIpsShFo5ugrfdlK",
    "eventId": "st6GLdflwQAvXqVbEBhlX",
    "activityType": "sentiment",
    "channelId": "4",
    "videoTimeStamp": "2023-01-03T10:21:20.989Z",
    "deviceId": "137",
    "GSI1PK": "EVENT#st6GLdflwQAvXqVbEBhlX#SESSION#PXjKAr2NFoHoIW7AssDFF",
    "GSI1SK": "ACTIVITY#SENTIMENT#2JrUWIRf5Adb5Ij7e2KEUyUuKEA"
  },
  {
    "PK": "EVENT#st6GLdflwQAvXqVbEBhlX#USER#VRMwIBTRTmLptAXmGY93Y",
    "SK": "ACTIVITY#2JrTahPwFXrDp2SFGOOXTq0mnnJ",
    "type": "Activity",
    "id": "2JrTahPwFXrDp2SFGOOXTq0mnnJ",
    "activityId": "7",
    "activityAt": "2023-01-04T12:27:46.102Z",
    "sessionId": "CMxH1NeLqFGMSmN6LootY",
    "userId": "VRMwIBTRTmLptAXmGY93Y",
    "eventId": "st6GLdflwQAvXqVbEBhlX",
    "activityType": "sentiment",
    "channelId": "8",
    "videoTimeStamp": "2023-01-04T12:19:33.596Z",
    "deviceId": "84z2oQ3LWP6UbMktz7-0h",
    "GSI1PK": "EVENT#st6GLdflwQAvXqVbEBhlX#SESSION#PXjKAr2NFoHoIW7AssDFF",
    "GSI1SK": "ACTIVITY#SENTIMENT#2JrTahPwFXrDp2SFGOOXTq0mnnJ"
  },
  {
    "PK": "EVENT#st6GLdflwQAvXqVbEBhlX#USER#VRMwIBTRTmLptAXmGY93Y",
    "SK": "ACTIVITY#2JrTadw0mtTpMziyujqplOMECL4",
    "type": "Activity",
    "id": "2JrTadw0mtTpMziyujqplOMECL4",
    "activityId": "7",
    "activityAt": "2023-01-04T12:27:46.064Z",
    "sessionId": "CMxH1NeLqFGMSmN6LootY",
    "userId": "VRMwIBTRTmLptAXmGY93Y",
    "eventId": "st6GLdflwQAvXqVbEBhlX",
    "activityType": "sentiment",
    "channelId": "8",
    "videoTimeStamp": "2023-01-04T12:19:33.596Z",
    "deviceId": "84z2oQ3LWP6UbMktz7-0h",
    "GSI1PK": "EVENT#st6GLdflwQAvXqVbEBhlX#SESSION#PXjKAr2NFoHoIW7AssDFF",
    "GSI1SK": "ACTIVITY#SENTIMENT#2JrTadw0mtTpMziyujqplOMECL4"
  },
  {
    "PK": "EVENT#st6GLdflwQAvXqVbEBhlX#USER#VRMwIBTRTmLptAXmGY93Y",
    "SK": "ACTIVITY#2JrTaYELx4V1caCBMgJDjvZZ4fu",
    "type": "Activity",
    "id": "2JrTaYELx4V1caCBMgJDjvZZ4fu",
    "activityId": "7",
    "activityAt": "2023-01-04T12:27:45.854Z",
    "sessionId": "CMxH1NeLqFGMSmN6LootY",
    "userId": "VRMwIBTRTmLptAXmGY93Y",
    "eventId": "st6GLdflwQAvXqVbEBhlX",
    "activityType": "sentiment",
    "channelId": "8",
    "videoTimeStamp": "2023-01-04T12:19:33.596Z",
    "deviceId": "84z2oQ3LWP6UbMktz7-0h",
    "GSI1PK": "EVENT#st6GLdflwQAvXqVbEBhlX#SESSION#PXjKAr2NFoHoIW7AssDFF",
    "GSI1SK": "ACTIVITY#SENTIMENT#2JrTaYELx4V1caCBMgJDjvZZ4fu"
  },
  {
    "PK": "EVENT#st6GLdflwQAvXqVbEBhlX#USER#VRMwIBTRTmLptAXmGY93Y",
    "SK": "ACTIVITY#2JrTaVAyPA80JFglD6UR0OmZZz7",
    "type": "Activity",
    "id": "2JrTaVAyPA80JFglD6UR0OmZZz7",
    "activityId": "7",
    "activityAt": "2023-01-04T12:27:45.748Z",
    "sessionId": "CMxH1NeLqFGMSmN6LootY",
    "userId": "VRMwIBTRTmLptAXmGY93Y",
    "eventId": "st6GLdflwQAvXqVbEBhlX",
    "activityType": "sentiment",
    "channelId": "8",
    "videoTimeStamp": "2023-01-04T12:19:33.596Z",
    "deviceId": "84z2oQ3LWP6UbMktz7-0h",
    "GSI1PK": "EVENT#st6GLdflwQAvXqVbEBhlX#SESSION#PXjKAr2NFoHoIW7AssDFF",
    "GSI1SK": "ACTIVITY#SENTIMENT#2JrTaVAyPA80JFglD6UR0OmZZz7"
  }
]